[
  {
    "DAY":"2009-12-31",
    "HOUR":6,
    "2":140,
    "3":29,
    "5":14,
    "7":0,
    "10":0,
    "13":0,
    "16":0,
    "19":0,
    "21":0,
    "25":0,
    "30":0,
    "35":0,
    "40":0,
    "45":0,
    "50":0,
    "55":0,
    "60":0,
    "65":0,
    "70":0,
    "75":0,
    "80":0,
    "85":0,
    "90":"0",
    "95":"0",
    "100":0
  },
  {
    "DAY":"2009-12-31",
    "HOUR":7,
    "2":462,
    "3":52,
    "5":61,
    "7":4,
    "10":0,
    "13":0,
    "16":0,
    "19":0,
    "21":0,
    "25":0,
    "30":0,
    "35":0,
    "40":0,
    "45":0,
    "50":0,
    "55":0,
    "60":0,
    "65":0,
    "70":0,
    "75":0,
    "80":0,
    "85":0,
    "90":"0",
    "95":"0",
    "100":0
  },
  {
    "DAY":"2009-12-31",
    "HOUR":8,
    "2":658,
    "3":57,
    "5":95,
    "7":18,
    "10":20,
    "13":5,
    "16":0,
    "19":0,
    "21":0,
    "25":0,
    "30":0,
    "35":0,
    "40":0,
    "45":0,
    "50":0,
    "55":0,
    "60":0,
    "65":0,
    "70":0,
    "75":0,
    "80":0,
    "85":0,
    "90":"0",
    "95":"0",
    "100":0
  },
  {
    "DAY":"2009-12-31",
    "HOUR":9,
    "2":104,
    "3":0,
    "5":0,
    "7":0,
    "10":0,
    "13":0,
    "16":0,
    "19":0,
    "21":0,
    "25":0,
    "30":0,
    "35":0,
    "40":0,
    "45":0,
    "50":0,
    "55":0,
    "60":0,
    "65":0,
    "70":0,
    "75":0,
    "80":0,
    "85":0,
    "90":"0",
    "95":"0",
    "100":0
  },
  {
    "DAY":"2009-12-31",
    "HOUR":10,
    "2":198,
    "3":32,
    "5":15,
    "7":6,
    "10":0,
    "13":0,
    "16":0,
    "19":0,
    "21":0,
    "25":0,
    "30":0,
    "35":0,
    "40":0,
    "45":0,
    "50":0,
    "55":0,
    "60":0,
    "65":0,
    "70":0,
    "75":0,
    "80":0,
    "85":0,
    "90":"0",
    "95":"0",
    "100":35
  },
  {
    "DAY":"2009-12-31",
    "HOUR":12,
    "2":74,
    "3":2,
    "5":5,
    "7":0,
    "10":0,
    "13":0,
    "16":0,
    "19":0,
    "21":0,
    "25":0,
    "30":0,
    "35":0,
    "40":0,
    "45":0,
    "50":0,
    "55":0,
    "60":0,
    "65":0,
    "70":0,
    "75":0,
    "80":0,
    "85":0,
    "90":"0",
    "95":"0",
    "100":0
  },
  {
    "DAY":"2009-12-31",
    "HOUR":13,
    "2":349,
    "3":35,
    "5":45,
    "7":32,
    "10":4,
    "13":0,
    "16":0,
    "19":0,
    "21":0,
    "25":0,
    "30":0,
    "35":0,
    "40":0,
    "45":0,
    "50":0,
    "55":0,
    "60":0,
    "65":0,
    "70":0,
    "75":0,
    "80":0,
    "85":0,
    "90":"0",
    "95":"0",
    "100":0
  },
  {
    "DAY":"2009-12-31",
    "HOUR":14,
    "2":783,
    "3":56,
    "5":72,
    "7":14,
    "10":3,
    "13":0,
    "16":0,
    "19":0,
    "21":0,
    "25":0,
    "30":0,
    "35":0,
    "40":0,
    "45":0,
    "50":0,
    "55":0,
    "60":0,
    "65":0,
    "70":0,
    "75":0,
    "80":0,
    "85":0,
    "90":"0",
    "95":"0",
    "100":0
  },
  {
    "DAY":"2009-12-31",
    "HOUR":15,
    "2":454,
    "3":53,
    "5":69,
    "7":27,
    "10":14,
    "13":6,
    "16":0,
    "19":0,
    "21":0,
    "25":0,
    "30":0,
    "35":0,
    "40":0,
    "45":0,
    "50":0,
    "55":0,
    "60":0,
    "65":0,
    "70":0,
    "75":0,
    "80":0,
    "85":0,
    "90":"0",
    "95":"0",
    "100":52
  },
  {
    "DAY":"2009-12-31",
    "HOUR":16,
    "2":17,
    "3":4,
    "5":3,
    "7":0,
    "10":0,
    "13":0,
    "16":0,
    "19":0,
    "21":0,
    "25":0,
    "30":0,
    "35":0,
    "40":0,
    "45":0,
    "50":0,
    "55":0,
    "60":0,
    "65":0,
    "70":0,
    "75":0,
    "80":0,
    "85":0,
    "90":"0",
    "95":"0",
    "100":0
  },
  {
    "DAY":"2009-12-31",
    "HOUR":17,
    "2":617,
    "3":39,
    "5":30,
    "7":10,
    "10":16,
    "13":9,
    "16":0,
    "19":0,
    "21":0,
    "25":0,
    "30":0,
    "35":0,
    "40":0,
    "45":0,
    "50":0,
    "55":0,
    "60":0,
    "65":0,
    "70":0,
    "75":0,
    "80":0,
    "85":0,
    "90":"0",
    "95":"0",
    "100":0
  },
  {
    "DAY":"2009-12-31",
    "HOUR":18,
    "2":213,
    "3":23,
    "5":49,
    "7":5,
    "10":0,
    "13":0,
    "16":0,
    "19":0,
    "21":0,
    "25":0,
    "30":0,
    "35":0,
    "40":0,
    "45":0,
    "50":0,
    "55":0,
    "60":0,
    "65":0,
    "70":0,
    "75":0,
    "80":0,
    "85":0,
    "90":"0",
    "95":"0",
    "100":0
  },
  {
    "DAY":"2009-12-31",
    "HOUR":19,
    "2":335,
    "3":67,
    "5":72,
    "7":0,
    "10":0,
    "13":0,
    "16":0,
    "19":0,
    "21":0,
    "25":0,
    "30":0,
    "35":0,
    "40":0,
    "45":0,
    "50":0,
    "55":0,
    "60":0,
    "65":0,
    "70":0,
    "75":0,
    "80":0,
    "85":0,
    "90":"0",
    "95":"0",
    "100":0
  },
  {
    "DAY":"2009-12-31",
    "HOUR":20,
    "2":565,
    "3":63,
    "5":91,
    "7":39,
    "10":21,
    "13":0,
    "16":0,
    "19":0,
    "21":0,
    "25":0,
    "30":0,
    "35":0,
    "40":0,
    "45":0,
    "50":0,
    "55":0,
    "60":0,
    "65":0,
    "70":0,
    "75":0,
    "80":0,
    "85":0,
    "90":"0",
    "95":"0",
    "100":0
  },
  {
    "DAY":"2009-12-31",
    "HOUR":21,
    "2":341,
    "3":39,
    "5":88,
    "7":28,
    "10":7,
    "13":0,
    "16":0,
    "19":0,
    "21":0,
    "25":0,
    "30":0,
    "35":0,
    "40":0,
    "45":0,
    "50":0,
    "55":0,
    "60":0,
    "65":0,
    "70":0,
    "75":0,
    "80":0,
    "85":0,
    "90":"0",
    "95":"0",
    "100":0
  },
  {
    "DAY":"2009-12-31",
    "HOUR":22,
    "2":977,
    "3":56,
    "5":138,
    "7":34,
    "10":4,
    "13":0,
    "16":0,
    "19":0,
    "21":0,
    "25":0,
    "30":0,
    "35":0,
    "40":0,
    "45":0,
    "50":0,
    "55":0,
    "60":0,
    "65":0,
    "70":0,
    "75":0,
    "80":0,
    "85":0,
    "90":"0",
    "95":"0",
    "100":0
  },
  {
    "DAY":"2009-12-31",
    "HOUR":23,
    "2":754,
    "3":84,
    "5":141,
    "7":54,
    "10":25,
    "13":7,
    "16":0,
    "19":0,
    "21":0,
    "25":0,
    "30":0,
    "35":0,
    "40":0,
    "45":0,
    "50":0,
    "55":0,
    "60":0,
    "65":0,
    "70":0,
    "75":0,
    "80":0,
    "85":0,
    "90":"0",
    "95":"0",
    "100":0
  },
  {
    "DAY":"2010-01-01",
    "HOUR":0,
    "2":858,
    "3":93,
    "5":182,
    "7":33,
    "10":3,
    "13":0,
    "16":0,
    "19":0,
    "21":0,
    "25":0,
    "30":0,
    "35":0,
    "40":0,
    "45":0,
    "50":0,
    "55":0,
    "60":0,
    "65":0,
    "70":0,
    "75":0,
    "80":0,
    "85":0,
    "90":"0",
    "95":"0",
    "100":0
  },
  {
    "DAY":"2010-01-01",
    "HOUR":1,
    "2":553,
    "3":55,
    "5":63,
    "7":23,
    "10":32,
    "13":1,
    "16":0,
    "19":0,
    "21":0,
    "25":0,
    "30":0,
    "35":0,
    "40":0,
    "45":0,
    "50":0,
    "55":0,
    "60":0,
    "65":0,
    "70":0,
    "75":0,
    "80":0,
    "85":0,
    "90":"0",
    "95":"0",
    "100":35
  },
  {
    "DAY":"2010-01-01",
    "HOUR":2,
    "2":950,
    "3":93,
    "5":141,
    "7":48,
    "10":29,
    "13":6,
    "16":9,
    "19":1,
    "21":0,
    "25":0,
    "30":0,
    "35":0,
    "40":0,
    "45":0,
    "50":0,
    "55":0,
    "60":0,
    "65":0,
    "70":0,
    "75":0,
    "80":0,
    "85":0,
    "90":"0",
    "95":"0",
    "100":0
  },
  {
    "DAY":"2010-01-01",
    "HOUR":3,
    "2":660,
    "3":110,
    "5":157,
    "7":56,
    "10":17,
    "13":3,
    "16":0,
    "19":0,
    "21":0,
    "25":0,
    "30":0,
    "35":0,
    "40":0,
    "45":0,
    "50":0,
    "55":0,
    "60":0,
    "65":0,
    "70":0,
    "75":0,
    "80":0,
    "85":0,
    "90":"0",
    "95":"0",
    "100":0
  },
  {
    "DAY":"2010-01-01",
    "HOUR":4,
    "2":1080,
    "3":102,
    "5":150,
    "7":56,
    "10":40,
    "13":4,
    "16":0,
    "19":0,
    "21":0,
    "25":0,
    "30":0,
    "35":0,
    "40":0,
    "45":0,
    "50":0,
    "55":0,
    "60":0,
    "65":0,
    "70":0,
    "75":0,
    "80":0,
    "85":0,
    "90":"0",
    "95":"0",
    "100":0
  },
  {
    "DAY":"2010-01-01",
    "HOUR":5,
    "2":1376,
    "3":67,
    "5":145,
    "7":86,
    "10":50,
    "13":11,
    "16":0,
    "19":0,
    "21":0,
    "25":0,
    "30":0,
    "35":0,
    "40":0,
    "45":0,
    "50":0,
    "55":0,
    "60":0,
    "65":0,
    "70":0,
    "75":0,
    "80":0,
    "85":0,
    "90":"0",
    "95":"0",
    "100":35
  },
  {
    "DAY":"2010-01-01",
    "HOUR":6,
    "2":578,
    "3":39,
    "5":73,
    "7":32,
    "10":17,
    "13":0,
    "16":0,
    "19":0,
    "21":0,
    "25":0,
    "30":0,
    "35":0,
    "40":0,
    "45":0,
    "50":0,
    "55":0,
    "60":0,
    "65":0,
    "70":0,
    "75":0,
    "80":0,
    "85":0,
    "90":"0",
    "95":"0",
    "100":0
  },
  {
    "DAY":"2010-01-01",
    "HOUR":7,
    "2":600,
    "3":64,
    "5":174,
    "7":49,
    "10":10,
    "13":0,
    "16":0,
    "19":0,
    "21":0,
    "25":0,
    "30":0,
    "35":0,
    "40":0,
    "45":0,
    "50":0,
    "55":0,
    "60":0,
    "65":0,
    "70":0,
    "75":0,
    "80":0,
    "85":0,
    "90":"0",
    "95":"0",
    "100":0
  },
  {
    "DAY":"2010-01-01",
    "HOUR":8,
    "2":1120,
    "3":95,
    "5":149,
    "7":70,
    "10":2,
    "13":0,
    "16":0,
    "19":0,
    "21":0,
    "25":0,
    "30":0,
    "35":0,
    "40":0,
    "45":0,
    "50":0,
    "55":0,
    "60":0,
    "65":0,
    "70":0,
    "75":0,
    "80":0,
    "85":0,
    "90":"0",
    "95":"0",
    "100":0
  },
  {
    "DAY":"2010-01-01",
    "HOUR":9,
    "2":425,
    "3":64,
    "5":61,
    "7":18,
    "10":9,
    "13":0,
    "16":0,
    "19":0,
    "21":0,
    "25":0,
    "30":0,
    "35":0,
    "40":0,
    "45":0,
    "50":0,
    "55":0,
    "60":0,
    "65":0,
    "70":0,
    "75":0,
    "80":0,
    "85":0,
    "90":"0",
    "95":"0",
    "100":0
  },
  {
    "DAY":"2010-01-01",
    "HOUR":10,
    "2":324,
    "3":42,
    "5":59,
    "7":27,
    "10":17,
    "13":6,
    "16":0,
    "19":0,
    "21":0,
    "25":0,
    "30":0,
    "35":0,
    "40":0,
    "45":0,
    "50":0,
    "55":0,
    "60":0,
    "65":0,
    "70":0,
    "75":0,
    "80":0,
    "85":0,
    "90":"0",
    "95":"0",
    "100":0
  },
  {
    "DAY":"2010-01-01",
    "HOUR":11,
    "2":439,
    "3":29,
    "5":59,
    "7":19,
    "10":0,
    "13":0,
    "16":0,
    "19":0,
    "21":0,
    "25":0,
    "30":0,
    "35":0,
    "40":0,
    "45":0,
    "50":0,
    "55":0,
    "60":0,
    "65":0,
    "70":0,
    "75":0,
    "80":0,
    "85":0,
    "90":"0",
    "95":"0",
    "100":0
  },
  {
    "DAY":"2010-01-01",
    "HOUR":12,
    "2":452,
    "3":66,
    "5":81,
    "7":24,
    "10":19,
    "13":0,
    "16":0,
    "19":0,
    "21":0,
    "25":0,
    "30":0,
    "35":0,
    "40":0,
    "45":0,
    "50":0,
    "55":0,
    "60":0,
    "65":0,
    "70":0,
    "75":0,
    "80":0,
    "85":0,
    "90":"0",
    "95":"0",
    "100":0
  },
  {
    "DAY":"2010-01-01",
    "HOUR":13,
    "2":667,
    "3":51,
    "5":150,
    "7":53,
    "10":20,
    "13":10,
    "16":2,
    "19":0,
    "21":0,
    "25":0,
    "30":0,
    "35":0,
    "40":0,
    "45":0,
    "50":0,
    "55":0,
    "60":0,
    "65":0,
    "70":0,
    "75":0,
    "80":0,
    "85":0,
    "90":"0",
    "95":"0",
    "100":0
  },
  {
    "DAY":"2010-01-01",
    "HOUR":14,
    "2":1333,
    "3":100,
    "5":198,
    "7":128,
    "10":65,
    "13":0,
    "16":0,
    "19":0,
    "21":0,
    "25":0,
    "30":0,
    "35":0,
    "40":0,
    "45":0,
    "50":0,
    "55":0,
    "60":0,
    "65":0,
    "70":0,
    "75":0,
    "80":0,
    "85":0,
    "90":"0",
    "95":"0",
    "100":0
  },
  {
    "DAY":"2010-01-01",
    "HOUR":15,
    "2":1520,
    "3":146,
    "5":262,
    "7":71,
    "10":46,
    "13":1,
    "16":0,
    "19":0,
    "21":0,
    "25":0,
    "30":0,
    "35":0,
    "40":0,
    "45":0,
    "50":0,
    "55":0,
    "60":0,
    "65":0,
    "70":0,
    "75":0,
    "80":0,
    "85":0,
    "90":"0",
    "95":"0",
    "100":0
  },
  {
    "DAY":"2010-01-01",
    "HOUR":16,
    "2":621,
    "3":58,
    "5":115,
    "7":17,
    "10":7,
    "13":0,
    "16":0,
    "19":0,
    "21":0,
    "25":0,
    "30":0,
    "35":0,
    "40":0,
    "45":0,
    "50":0,
    "55":0,
    "60":0,
    "65":0,
    "70":0,
    "75":0,
    "80":0,
    "85":0,
    "90":"0",
    "95":"0",
    "100":0
  },
  {
    "DAY":"2010-01-01",
    "HOUR":17,
    "2":1317,
    "3":76,
    "5":177,
    "7":82,
    "10":77,
    "13":48,
    "16":13,
    "19":0,
    "21":0,
    "25":0,
    "30":0,
    "35":0,
    "40":0,
    "45":0,
    "50":0,
    "55":0,
    "60":0,
    "65":0,
    "70":0,
    "75":0,
    "80":0,
    "85":0,
    "90":"0",
    "95":"0",
    "100":0
  },
  {
    "DAY":"2010-01-01",
    "HOUR":18,
    "2":336,
    "3":52,
    "5":59,
    "7":5,
    "10":0,
    "13":0,
    "16":0,
    "19":0,
    "21":0,
    "25":0,
    "30":0,
    "35":0,
    "40":0,
    "45":0,
    "50":0,
    "55":0,
    "60":0,
    "65":0,
    "70":0,
    "75":0,
    "80":0,
    "85":0,
    "90":"0",
    "95":"0",
    "100":0
  },
  {
    "DAY":"2010-01-01",
    "HOUR":19,
    "2":727,
    "3":98,
    "5":238,
    "7":60,
    "10":25,
    "13":0,
    "16":0,
    "19":0,
    "21":0,
    "25":0,
    "30":0,
    "35":0,
    "40":0,
    "45":0,
    "50":0,
    "55":0,
    "60":0,
    "65":0,
    "70":0,
    "75":0,
    "80":0,
    "85":0,
    "90":"0",
    "95":"0",
    "100":0
  },
  {
    "DAY":"2010-01-01",
    "HOUR":20,
    "2":1498,
    "3":222,
    "5":181,
    "7":78,
    "10":19,
    "13":0,
    "16":0,
    "19":0,
    "21":0,
    "25":0,
    "30":0,
    "35":0,
    "40":0,
    "45":0,
    "50":0,
    "55":0,
    "60":0,
    "65":0,
    "70":0,
    "75":0,
    "80":0,
    "85":0,
    "90":"0",
    "95":"0",
    "100":0
  },
  {
    "DAY":"2010-01-01",
    "HOUR":21,
    "2":736,
    "3":67,
    "5":170,
    "7":56,
    "10":30,
    "13":5,
    "16":0,
    "19":0,
    "21":0,
    "25":0,
    "30":0,
    "35":0,
    "40":0,
    "45":0,
    "50":0,
    "55":0,
    "60":0,
    "65":0,
    "70":0,
    "75":0,
    "80":0,
    "85":0,
    "90":"0",
    "95":"0",
    "100":25
  },
  {
    "DAY":"2010-01-01",
    "HOUR":22,
    "2":1458,
    "3":97,
    "5":177,
    "7":97,
    "10":62,
    "13":27,
    "16":0,
    "19":0,
    "21":0,
    "25":0,
    "30":0,
    "35":0,
    "40":0,
    "45":0,
    "50":0,
    "55":0,
    "60":0,
    "65":0,
    "70":0,
    "75":0,
    "80":0,
    "85":0,
    "90":"0",
    "95":"0",
    "100":0
  },
  {
    "DAY":"2010-01-01",
    "HOUR":23,
    "2":1314,
    "3":84,
    "5":163,
    "7":48,
    "10":36,
    "13":14,
    "16":4,
    "19":0,
    "21":0,
    "25":0,
    "30":0,
    "35":0,
    "40":0,
    "45":0,
    "50":0,
    "55":0,
    "60":0,
    "65":0,
    "70":0,
    "75":0,
    "80":0,
    "85":0,
    "90":"0",
    "95":"0",
    "100":45
  },
  {
    "DAY":"2010-01-02",
    "HOUR":0,
    "2":587,
    "3":54,
    "5":103,
    "7":46,
    "10":41,
    "13":11,
    "16":1,
    "19":0,
    "21":0,
    "25":0,
    "30":0,
    "35":0,
    "40":0,
    "45":0,
    "50":0,
    "55":0,
    "60":0,
    "65":0,
    "70":0,
    "75":0,
    "80":0,
    "85":0,
    "90":"0",
    "95":"0",
    "100":0
  },
  {
    "DAY":"2010-01-02",
    "HOUR":1,
    "2":1582,
    "3":72,
    "5":191,
    "7":136,
    "10":129,
    "13":38,
    "16":0,
    "19":0,
    "21":0,
    "25":0,
    "30":0,
    "35":0,
    "40":0,
    "45":0,
    "50":0,
    "55":0,
    "60":0,
    "65":0,
    "70":0,
    "75":0,
    "80":0,
    "85":0,
    "90":"0",
    "95":"0",
    "100":0
  },
  {
    "DAY":"2010-01-02",
    "HOUR":2,
    "2":1138,
    "3":91,
    "5":123,
    "7":43,
    "10":24,
    "13":3,
    "16":0,
    "19":0,
    "21":0,
    "25":0,
    "30":0,
    "35":0,
    "40":0,
    "45":0,
    "50":0,
    "55":0,
    "60":0,
    "65":0,
    "70":0,
    "75":0,
    "80":0,
    "85":0,
    "90":"0",
    "95":"0",
    "100":54
  },
  {
    "DAY":"2010-01-02",
    "HOUR":3,
    "2":601,
    "3":57,
    "5":138,
    "7":73,
    "10":24,
    "13":0,
    "16":0,
    "19":0,
    "21":0,
    "25":0,
    "30":0,
    "35":0,
    "40":0,
    "45":0,
    "50":0,
    "55":0,
    "60":0,
    "65":0,
    "70":0,
    "75":0,
    "80":0,
    "85":0,
    "90":"0",
    "95":"0",
    "100":0
  },
  {
    "DAY":"2010-01-02",
    "HOUR":4,
    "2":933,
    "3":79,
    "5":188,
    "7":82,
    "10":32,
    "13":5,
    "16":0,
    "19":0,
    "21":0,
    "25":0,
    "30":0,
    "35":0,
    "40":0,
    "45":0,
    "50":0,
    "55":0,
    "60":0,
    "65":0,
    "70":0,
    "75":0,
    "80":0,
    "85":0,
    "90":"0",
    "95":"0",
    "100":0
  },
  {
    "DAY":"2010-01-02",
    "HOUR":5,
    "2":1217,
    "3":119,
    "5":220,
    "7":79,
    "10":73,
    "13":23,
    "16":11,
    "19":0,
    "21":0,
    "25":0,
    "30":0,
    "35":0,
    "40":0,
    "45":0,
    "50":0,
    "55":0,
    "60":0,
    "65":0,
    "70":0,
    "75":0,
    "80":0,
    "85":0,
    "90":"0",
    "95":"0",
    "100":0
  },
  {
    "DAY":"2010-01-02",
    "HOUR":6,
    "2":733,
    "3":57,
    "5":166,
    "7":63,
    "10":51,
    "13":6,
    "16":9,
    "19":0,
    "21":0,
    "25":0,
    "30":0,
    "35":0,
    "40":0,
    "45":0,
    "50":0,
    "55":0,
    "60":0,
    "65":0,
    "70":0,
    "75":0,
    "80":0,
    "85":0,
    "90":"0",
    "95":"0",
    "100":0
  },
  {
    "DAY":"2010-01-02",
    "HOUR":7,
    "2":878,
    "3":73,
    "5":119,
    "7":83,
    "10":29,
    "13":13,
    "16":0,
    "19":0,
    "21":0,
    "25":0,
    "30":0,
    "35":0,
    "40":0,
    "45":0,
    "50":0,
    "55":0,
    "60":0,
    "65":0,
    "70":0,
    "75":0,
    "80":0,
    "85":0,
    "90":"0",
    "95":"0",
    "100":0
  },
  {
    "DAY":"2010-01-02",
    "HOUR":8,
    "2":962,
    "3":91,
    "5":153,
    "7":75,
    "10":78,
    "13":21,
    "16":5,
    "19":0,
    "21":0,
    "25":0,
    "30":0,
    "35":0,
    "40":0,
    "45":0,
    "50":0,
    "55":0,
    "60":0,
    "65":0,
    "70":0,
    "75":0,
    "80":0,
    "85":0,
    "90":"0",
    "95":"0",
    "100":36
  },
  {
    "DAY":"2010-01-02",
    "HOUR":9,
    "2":1370,
    "3":93,
    "5":211,
    "7":99,
    "10":44,
    "13":12,
    "16":6,
    "19":4,
    "21":7,
    "25":1,
    "30":0,
    "35":0,
    "40":0,
    "45":0,
    "50":0,
    "55":0,
    "60":0,
    "65":0,
    "70":0,
    "75":0,
    "80":0,
    "85":0,
    "90":"0",
    "95":"0",
    "100":0
  },
  {
    "DAY":"2010-01-02",
    "HOUR":10,
    "2":1558,
    "3":132,
    "5":190,
    "7":151,
    "10":92,
    "13":27,
    "16":3,
    "19":0,
    "21":0,
    "25":0,
    "30":0,
    "35":0,
    "40":0,
    "45":0,
    "50":0,
    "55":0,
    "60":0,
    "65":0,
    "70":0,
    "75":0,
    "80":0,
    "85":0,
    "90":"0",
    "95":"0",
    "100":0
  },
  {
    "DAY":"2010-01-02",
    "HOUR":11,
    "2":1528,
    "3":74,
    "5":145,
    "7":105,
    "10":76,
    "13":51,
    "16":12,
    "19":13,
    "21":3,
    "25":3,
    "30":6,
    "35":7,
    "40":5,
    "45":1,
    "50":1,
    "55":2,
    "60":4,
    "65":2,
    "70":2,
    "75":2,
    "80":4,
    "85":0,
    "90":"0",
    "95":"0",
    "100":71
  },
  {
    "DAY":"2010-01-02",
    "HOUR":12,
    "2":1226,
    "3":92,
    "5":164,
    "7":110,
    "10":101,
    "13":48,
    "16":3,
    "19":0,
    "21":0,
    "25":0,
    "30":0,
    "35":0,
    "40":0,
    "45":0,
    "50":0,
    "55":0,
    "60":0,
    "65":0,
    "70":0,
    "75":0,
    "80":0,
    "85":0,
    "90":"0",
    "95":"0",
    "100":0
  },
  {
    "DAY":"2010-01-02",
    "HOUR":13,
    "2":1541,
    "3":74,
    "5":152,
    "7":130,
    "10":119,
    "13":74,
    "16":23,
    "19":4,
    "21":0,
    "25":0,
    "30":0,
    "35":0,
    "40":0,
    "45":0,
    "50":0,
    "55":0,
    "60":0,
    "65":0,
    "70":0,
    "75":0,
    "80":0,
    "85":0,
    "90":"0",
    "95":"0",
    "100":0
  },
  {
    "DAY":"2010-01-02",
    "HOUR":14,
    "2":1060,
    "3":71,
    "5":161,
    "7":74,
    "10":55,
    "13":28,
    "16":0,
    "19":0,
    "21":0,
    "25":0,
    "30":0,
    "35":0,
    "40":0,
    "45":0,
    "50":0,
    "55":0,
    "60":0,
    "65":0,
    "70":0,
    "75":0,
    "80":0,
    "85":0,
    "90":"0",
    "95":"0",
    "100":0
  },
  {
    "DAY":"2010-01-02",
    "HOUR":15,
    "2":825,
    "3":46,
    "5":109,
    "7":50,
    "10":54,
    "13":22,
    "16":0,
    "19":0,
    "21":0,
    "25":0,
    "30":0,
    "35":0,
    "40":0,
    "45":0,
    "50":0,
    "55":0,
    "60":0,
    "65":0,
    "70":0,
    "75":0,
    "80":0,
    "85":0,
    "90":"0",
    "95":"0",
    "100":0
  },
  {
    "DAY":"2010-01-02",
    "HOUR":16,
    "2":705,
    "3":73,
    "5":118,
    "7":61,
    "10":38,
    "13":13,
    "16":24,
    "19":4,
    "21":0,
    "25":0,
    "30":0,
    "35":0,
    "40":0,
    "45":0,
    "50":0,
    "55":0,
    "60":0,
    "65":0,
    "70":0,
    "75":0,
    "80":0,
    "85":0,
    "90":"0",
    "95":"0",
    "100":36
  },
  {
    "DAY":"2010-01-02",
    "HOUR":17,
    "2":771,
    "3":34,
    "5":92,
    "7":47,
    "10":39,
    "13":13,
    "16":5,
    "19":0,
    "21":0,
    "25":0,
    "30":0,
    "35":0,
    "40":0,
    "45":0,
    "50":0,
    "55":0,
    "60":0,
    "65":0,
    "70":0,
    "75":0,
    "80":0,
    "85":0,
    "90":"0",
    "95":"0",
    "100":36
  },
  {
    "DAY":"2010-01-02",
    "HOUR":18,
    "2":1905,
    "3":81,
    "5":174,
    "7":129,
    "10":154,
    "13":72,
    "16":24,
    "19":3,
    "21":0,
    "25":0,
    "30":0,
    "35":0,
    "40":0,
    "45":0,
    "50":0,
    "55":0,
    "60":0,
    "65":0,
    "70":0,
    "75":0,
    "80":0,
    "85":0,
    "90":"0",
    "95":"0",
    "100":32
  },
  {
    "DAY":"2010-01-02",
    "HOUR":19,
    "2":1862,
    "3":89,
    "5":190,
    "7":133,
    "10":89,
    "13":71,
    "16":29,
    "19":0,
    "21":0,
    "25":0,
    "30":0,
    "35":0,
    "40":0,
    "45":0,
    "50":0,
    "55":0,
    "60":0,
    "65":0,
    "70":0,
    "75":0,
    "80":0,
    "85":0,
    "90":"0",
    "95":"0",
    "100":0
  },
  {
    "DAY":"2010-01-02",
    "HOUR":20,
    "2":1877,
    "3":107,
    "5":187,
    "7":99,
    "10":145,
    "13":99,
    "16":31,
    "19":5,
    "21":0,
    "25":0,
    "30":0,
    "35":0,
    "40":0,
    "45":0,
    "50":0,
    "55":0,
    "60":0,
    "65":0,
    "70":0,
    "75":0,
    "80":0,
    "85":0,
    "90":"0",
    "95":"0",
    "100":37
  },
  {
    "DAY":"2010-01-02",
    "HOUR":21,
    "2":1416,
    "3":70,
    "5":151,
    "7":73,
    "10":75,
    "13":72,
    "16":26,
    "19":0,
    "21":0,
    "25":0,
    "30":0,
    "35":0,
    "40":0,
    "45":0,
    "50":0,
    "55":0,
    "60":0,
    "65":0,
    "70":0,
    "75":0,
    "80":0,
    "85":0,
    "90":"0",
    "95":"0",
    "100":0
  },
  {
    "DAY":"2010-01-02",
    "HOUR":22,
    "2":2066,
    "3":77,
    "5":163,
    "7":136,
    "10":114,
    "13":85,
    "16":44,
    "19":2,
    "21":0,
    "25":0,
    "30":0,
    "35":0,
    "40":0,
    "45":0,
    "50":0,
    "55":0,
    "60":0,
    "65":0,
    "70":0,
    "75":0,
    "80":0,
    "85":0,
    "90":"0",
    "95":"0",
    "100":0
  },
  {
    "DAY":"2010-01-02",
    "HOUR":23,
    "2":1799,
    "3":98,
    "5":161,
    "7":91,
    "10":125,
    "13":83,
    "16":36,
    "19":9,
    "21":0,
    "25":4,
    "30":0,
    "35":0,
    "40":0,
    "45":0,
    "50":0,
    "55":0,
    "60":0,
    "65":0,
    "70":0,
    "75":0,
    "80":0,
    "85":0,
    "90":"0",
    "95":"0",
    "100":0
  },
  {
    "DAY":"2010-01-03",
    "HOUR":0,
    "2":1884,
    "3":116,
    "5":212,
    "7":170,
    "10":130,
    "13":29,
    "16":0,
    "19":0,
    "21":0,
    "25":0,
    "30":0,
    "35":0,
    "40":0,
    "45":0,
    "50":0,
    "55":0,
    "60":0,
    "65":0,
    "70":0,
    "75":0,
    "80":0,
    "85":0,
    "90":"0",
    "95":"0",
    "100":0
  },
  {
    "DAY":"2010-01-03",
    "HOUR":1,
    "2":995,
    "3":59,
    "5":138,
    "7":69,
    "10":120,
    "13":40,
    "16":19,
    "19":4,
    "21":0,
    "25":0,
    "30":0,
    "35":0,
    "40":0,
    "45":0,
    "50":0,
    "55":0,
    "60":0,
    "65":0,
    "70":0,
    "75":0,
    "80":0,
    "85":0,
    "90":"0",
    "95":"0",
    "100":0
  },
  {
    "DAY":"2010-01-03",
    "HOUR":2,
    "2":2051,
    "3":86,
    "5":168,
    "7":156,
    "10":163,
    "13":91,
    "16":14,
    "19":11,
    "21":0,
    "25":0,
    "30":0,
    "35":0,
    "40":0,
    "45":0,
    "50":0,
    "55":0,
    "60":0,
    "65":0,
    "70":0,
    "75":0,
    "80":0,
    "85":0,
    "90":"0",
    "95":"0",
    "100":0
  },
  {
    "DAY":"2010-01-03",
    "HOUR":3,
    "2":3179,
    "3":115,
    "5":282,
    "7":192,
    "10":245,
    "13":75,
    "16":12,
    "19":0,
    "21":0,
    "25":0,
    "30":0,
    "35":0,
    "40":0,
    "45":0,
    "50":0,
    "55":0,
    "60":0,
    "65":0,
    "70":0,
    "75":0,
    "80":0,
    "85":0,
    "90":"0",
    "95":"0",
    "100":0
  },
  {
    "DAY":"2010-01-03",
    "HOUR":4,
    "2":3010,
    "3":251,
    "5":399,
    "7":170,
    "10":210,
    "13":115,
    "16":28,
    "19":0,
    "21":0,
    "25":0,
    "30":0,
    "35":0,
    "40":0,
    "45":0,
    "50":0,
    "55":0,
    "60":0,
    "65":0,
    "70":0,
    "75":0,
    "80":0,
    "85":0,
    "90":"0",
    "95":"0",
    "100":0
  },
  {
    "DAY":"2010-01-03",
    "HOUR":5,
    "2":3291,
    "3":346,
    "5":446,
    "7":279,
    "10":196,
    "13":49,
    "16":0,
    "19":0,
    "21":0,
    "25":0,
    "30":0,
    "35":0,
    "40":0,
    "45":0,
    "50":0,
    "55":0,
    "60":0,
    "65":0,
    "70":0,
    "75":0,
    "80":0,
    "85":0,
    "90":"0",
    "95":"0",
    "100":57
  },
  {
    "DAY":"2010-01-03",
    "HOUR":6,
    "2":3843,
    "3":253,
    "5":500,
    "7":406,
    "10":246,
    "13":49,
    "16":6,
    "19":2,
    "21":0,
    "25":0,
    "30":0,
    "35":0,
    "40":0,
    "45":0,
    "50":0,
    "55":0,
    "60":0,
    "65":0,
    "70":0,
    "75":0,
    "80":0,
    "85":0,
    "90":"0",
    "95":"0",
    "100":0
  },
  {
    "DAY":"2010-01-03",
    "HOUR":7,
    "2":3155,
    "3":322,
    "5":571,
    "7":283,
    "10":296,
    "13":78,
    "16":27,
    "19":0,
    "21":0,
    "25":0,
    "30":0,
    "35":0,
    "40":0,
    "45":0,
    "50":0,
    "55":0,
    "60":0,
    "65":0,
    "70":0,
    "75":0,
    "80":0,
    "85":0,
    "90":"0",
    "95":"0",
    "100":0
  },
  {
    "DAY":"2010-01-03",
    "HOUR":8,
    "2":3364,
    "3":290,
    "5":500,
    "7":239,
    "10":122,
    "13":50,
    "16":15,
    "19":0,
    "21":0,
    "25":0,
    "30":0,
    "35":0,
    "40":0,
    "45":0,
    "50":0,
    "55":0,
    "60":0,
    "65":0,
    "70":0,
    "75":0,
    "80":0,
    "85":0,
    "90":"0",
    "95":"0",
    "100":48
  },
  {
    "DAY":"2010-01-03",
    "HOUR":9,
    "2":3638,
    "3":274,
    "5":328,
    "7":272,
    "10":295,
    "13":32,
    "16":47,
    "19":38,
    "21":7,
    "25":4,
    "30":9,
    "35":1,
    "40":0,
    "45":0,
    "50":0,
    "55":0,
    "60":0,
    "65":0,
    "70":0,
    "75":0,
    "80":0,
    "85":0,
    "90":"0",
    "95":"0",
    "100":0
  },
  {
    "DAY":"2010-01-03",
    "HOUR":10,
    "2":3279,
    "3":170,
    "5":429,
    "7":314,
    "10":274,
    "13":75,
    "16":64,
    "19":17,
    "21":7,
    "25":2,
    "30":6,
    "35":0,
    "40":0,
    "45":0,
    "50":0,
    "55":0,
    "60":0,
    "65":0,
    "70":0,
    "75":0,
    "80":0,
    "85":0,
    "90":"0",
    "95":"0",
    "100":0
  },
  {
    "DAY":"2010-01-03",
    "HOUR":11,
    "2":2474,
    "3":165,
    "5":286,
    "7":170,
    "10":159,
    "13":45,
    "16":18,
    "19":2,
    "21":0,
    "25":0,
    "30":0,
    "35":0,
    "40":0,
    "45":0,
    "50":0,
    "55":0,
    "60":0,
    "65":0,
    "70":0,
    "75":0,
    "80":0,
    "85":0,
    "90":"0",
    "95":"0",
    "100":68
  },
  {
    "DAY":"2010-01-03",
    "HOUR":12,
    "2":3327,
    "3":136,
    "5":412,
    "7":291,
    "10":169,
    "13":114,
    "16":22,
    "19":6,
    "21":0,
    "25":0,
    "30":0,
    "35":0,
    "40":0,
    "45":0,
    "50":0,
    "55":0,
    "60":0,
    "65":0,
    "70":0,
    "75":0,
    "80":0,
    "85":0,
    "90":"0",
    "95":"0",
    "100":0
  },
  {
    "DAY":"2010-01-03",
    "HOUR":13,
    "2":3691,
    "3":165,
    "5":299,
    "7":228,
    "10":274,
    "13":157,
    "16":64,
    "19":11,
    "21":18,
    "25":17,
    "30":0,
    "35":0,
    "40":0,
    "45":0,
    "50":0,
    "55":0,
    "60":0,
    "65":0,
    "70":0,
    "75":0,
    "80":0,
    "85":0,
    "90":"0",
    "95":"0",
    "100":0
  },
  {
    "DAY":"2010-01-03",
    "HOUR":14,
    "2":2262,
    "3":247,
    "5":311,
    "7":142,
    "10":144,
    "13":5,
    "16":0,
    "19":0,
    "21":0,
    "25":0,
    "30":0,
    "35":0,
    "40":0,
    "45":0,
    "50":0,
    "55":0,
    "60":0,
    "65":0,
    "70":0,
    "75":0,
    "80":0,
    "85":0,
    "90":"0",
    "95":"0",
    "100":72
  },
  {
    "DAY":"2010-01-03",
    "HOUR":15,
    "2":3944,
    "3":193,
    "5":322,
    "7":376,
    "10":254,
    "13":97,
    "16":32,
    "19":0,
    "21":2,
    "25":0,
    "30":11,
    "35":3,
    "40":0,
    "45":0,
    "50":0,
    "55":0,
    "60":0,
    "65":0,
    "70":0,
    "75":0,
    "80":0,
    "85":0,
    "90":"0",
    "95":"0",
    "100":0
  },
  {
    "DAY":"2010-01-03",
    "HOUR":16,
    "2":3430,
    "3":207,
    "5":376,
    "7":292,
    "10":236,
    "13":65,
    "16":36,
    "19":35,
    "21":21,
    "25":15,
    "30":6,
    "35":0,
    "40":1,
    "45":5,
    "50":4,
    "55":0,
    "60":0,
    "65":0,
    "70":0,
    "75":0,
    "80":0,
    "85":0,
    "90":"0",
    "95":"0",
    "100":0
  },
  {
    "DAY":"2010-01-03",
    "HOUR":17,
    "2":2213,
    "3":231,
    "5":349,
    "7":136,
    "10":107,
    "13":60,
    "16":28,
    "19":8,
    "21":10,
    "25":2,
    "30":0,
    "35":0,
    "40":0,
    "45":0,
    "50":0,
    "55":0,
    "60":0,
    "65":0,
    "70":0,
    "75":0,
    "80":0,
    "85":0,
    "90":"0",
    "95":"0",
    "100":152
  },
  {
    "DAY":"2010-01-03",
    "HOUR":18,
    "2":2283,
    "3":176,
    "5":289,
    "7":195,
    "10":166,
    "13":66,
    "16":74,
    "19":16,
    "21":4,
    "25":34,
    "30":0,
    "35":0,
    "40":0,
    "45":0,
    "50":0,
    "55":0,
    "60":0,
    "65":0,
    "70":0,
    "75":0,
    "80":0,
    "85":0,
    "90":"0",
    "95":"0",
    "100":0
  },
  {
    "DAY":"2010-01-03",
    "HOUR":19,
    "2":3406,
    "3":147,
    "5":312,
    "7":274,
    "10":318,
    "13":144,
    "16":51,
    "19":4,
    "21":0,
    "25":0,
    "30":0,
    "35":0,
    "40":0,
    "45":0,
    "50":0,
    "55":0,
    "60":0,
    "65":0,
    "70":0,
    "75":0,
    "80":0,
    "85":0,
    "90":"0",
    "95":"0",
    "100":0
  },
  {
    "DAY":"2010-01-03",
    "HOUR":20,
    "2":3598,
    "3":223,
    "5":490,
    "7":315,
    "10":205,
    "13":164,
    "16":22,
    "19":24,
    "21":2,
    "25":0,
    "30":0,
    "35":0,
    "40":0,
    "45":0,
    "50":0,
    "55":0,
    "60":0,
    "65":0,
    "70":0,
    "75":0,
    "80":0,
    "85":0,
    "90":"0",
    "95":"0",
    "100":0
  },
  {
    "DAY":"2010-01-03",
    "HOUR":21,
    "2":3162,
    "3":266,
    "5":345,
    "7":223,
    "10":216,
    "13":122,
    "16":52,
    "19":12,
    "21":0,
    "25":0,
    "30":0,
    "35":0,
    "40":0,
    "45":0,
    "50":0,
    "55":0,
    "60":0,
    "65":0,
    "70":0,
    "75":0,
    "80":0,
    "85":0,
    "90":"0",
    "95":"0",
    "100":0
  },
  {
    "DAY":"2010-01-03",
    "HOUR":22,
    "2":3194,
    "3":124,
    "5":332,
    "7":335,
    "10":257,
    "13":119,
    "16":20,
    "19":8,
    "21":0,
    "25":0,
    "30":0,
    "35":0,
    "40":0,
    "45":0,
    "50":0,
    "55":0,
    "60":0,
    "65":0,
    "70":0,
    "75":0,
    "80":0,
    "85":0,
    "90":"0",
    "95":"0",
    "100":0
  },
  {
    "DAY":"2010-01-03",
    "HOUR":23,
    "2":2455,
    "3":248,
    "5":397,
    "7":170,
    "10":166,
    "13":48,
    "16":22,
    "19":0,
    "21":0,
    "25":0,
    "30":0,
    "35":0,
    "40":0,
    "45":0,
    "50":0,
    "55":0,
    "60":0,
    "65":0,
    "70":0,
    "75":0,
    "80":0,
    "85":0,
    "90":"0",
    "95":"0",
    "100":0
  },
  {
    "DAY":"2010-01-04",
    "HOUR":0,
    "2":3233,
    "3":158,
    "5":331,
    "7":283,
    "10":232,
    "13":110,
    "16":52,
    "19":14,
    "21":6,
    "25":6,
    "30":0,
    "35":0,
    "40":0,
    "45":0,
    "50":0,
    "55":0,
    "60":0,
    "65":0,
    "70":0,
    "75":0,
    "80":0,
    "85":0,
    "90":"0",
    "95":"0",
    "100":68
  },
  {
    "DAY":"2010-01-04",
    "HOUR":1,
    "2":3500,
    "3":171,
    "5":312,
    "7":296,
    "10":208,
    "13":140,
    "16":44,
    "19":0,
    "21":0,
    "25":0,
    "30":0,
    "35":0,
    "40":0,
    "45":0,
    "50":0,
    "55":0,
    "60":0,
    "65":0,
    "70":0,
    "75":0,
    "80":0,
    "85":0,
    "90":"0",
    "95":"0",
    "100":0
  },
  {
    "DAY":"2010-01-04",
    "HOUR":2,
    "2":3321,
    "3":170,
    "5":457,
    "7":362,
    "10":280,
    "13":162,
    "16":20,
    "19":0,
    "21":0,
    "25":0,
    "30":0,
    "35":0,
    "40":0,
    "45":0,
    "50":0,
    "55":0,
    "60":0,
    "65":0,
    "70":0,
    "75":0,
    "80":0,
    "85":0,
    "90":"0",
    "95":"0",
    "100":0
  },
  {
    "DAY":"2010-01-04",
    "HOUR":3,
    "2":2005,
    "3":175,
    "5":262,
    "7":127,
    "10":121,
    "13":99,
    "16":34,
    "19":0,
    "21":0,
    "25":0,
    "30":0,
    "35":0,
    "40":0,
    "45":0,
    "50":0,
    "55":0,
    "60":0,
    "65":0,
    "70":0,
    "75":0,
    "80":0,
    "85":0,
    "90":"0",
    "95":"0",
    "100":67
  },
  {
    "DAY":"2010-01-04",
    "HOUR":4,
    "2":3366,
    "3":175,
    "5":303,
    "7":209,
    "10":349,
    "13":120,
    "16":14,
    "19":0,
    "21":0,
    "25":0,
    "30":0,
    "35":0,
    "40":0,
    "45":0,
    "50":0,
    "55":0,
    "60":0,
    "65":0,
    "70":0,
    "75":0,
    "80":0,
    "85":0,
    "90":"0",
    "95":"0",
    "100":0
  },
  {
    "DAY":"2010-01-04",
    "HOUR":5,
    "2":3311,
    "3":192,
    "5":567,
    "7":330,
    "10":184,
    "13":90,
    "16":24,
    "19":0,
    "21":0,
    "25":0,
    "30":0,
    "35":0,
    "40":0,
    "45":0,
    "50":0,
    "55":0,
    "60":0,
    "65":0,
    "70":0,
    "75":0,
    "80":0,
    "85":0,
    "90":"0",
    "95":"0",
    "100":0
  },
  {
    "DAY":"2010-01-04",
    "HOUR":6,
    "2":2811,
    "3":264,
    "5":490,
    "7":130,
    "10":78,
    "13":0,
    "16":0,
    "19":0,
    "21":0,
    "25":0,
    "30":0,
    "35":0,
    "40":0,
    "45":0,
    "50":0,
    "55":0,
    "60":0,
    "65":0,
    "70":0,
    "75":0,
    "80":0,
    "85":0,
    "90":"0",
    "95":"0",
    "100":0
  },
  {
    "DAY":"2010-01-04",
    "HOUR":7,
    "2":2852,
    "3":213,
    "5":398,
    "7":281,
    "10":178,
    "13":40,
    "16":2,
    "19":0,
    "21":0,
    "25":0,
    "30":0,
    "35":0,
    "40":0,
    "45":0,
    "50":0,
    "55":0,
    "60":0,
    "65":0,
    "70":0,
    "75":0,
    "80":0,
    "85":0,
    "90":"0",
    "95":"0",
    "100":0
  },
  {
    "DAY":"2010-01-04",
    "HOUR":8,
    "2":2299,
    "3":174,
    "5":318,
    "7":229,
    "10":202,
    "13":50,
    "16":10,
    "19":8,
    "21":0,
    "25":0,
    "30":0,
    "35":0,
    "40":0,
    "45":0,
    "50":0,
    "55":0,
    "60":0,
    "65":0,
    "70":0,
    "75":0,
    "80":0,
    "85":0,
    "90":"0",
    "95":"0",
    "100":70
  },
  {
    "DAY":"2010-01-04",
    "HOUR":9,
    "2":1594,
    "3":242,
    "5":260,
    "7":124,
    "10":90,
    "13":38,
    "16":0,
    "19":0,
    "21":0,
    "25":0,
    "30":0,
    "35":0,
    "40":0,
    "45":0,
    "50":0,
    "55":0,
    "60":0,
    "65":0,
    "70":0,
    "75":0,
    "80":0,
    "85":0,
    "90":"0",
    "95":"0",
    "100":0
  },
  {
    "DAY":"2010-01-04",
    "HOUR":10,
    "2":2638,
    "3":162,
    "5":320,
    "7":220,
    "10":160,
    "13":66,
    "16":46,
    "19":28,
    "21":0,
    "25":0,
    "30":0,
    "35":0,
    "40":0,
    "45":0,
    "50":0,
    "55":0,
    "60":0,
    "65":0,
    "70":0,
    "75":0,
    "80":0,
    "85":0,
    "90":"0",
    "95":"0",
    "100":0
  },
  {
    "DAY":"2010-01-04",
    "HOUR":11,
    "2":1856,
    "3":228,
    "5":472,
    "7":272,
    "10":134,
    "13":20,
    "16":0,
    "19":0,
    "21":0,
    "25":0,
    "30":0,
    "35":0,
    "40":0,
    "45":0,
    "50":0,
    "55":0,
    "60":0,
    "65":0,
    "70":0,
    "75":0,
    "80":0,
    "85":0,
    "90":"0",
    "95":"0",
    "100":0
  },
  {
    "DAY":"2010-01-04",
    "HOUR":12,
    "2":2534,
    "3":249,
    "5":392,
    "7":87,
    "10":100,
    "13":6,
    "16":6,
    "19":4,
    "21":4,
    "25":10,
    "30":0,
    "35":0,
    "40":0,
    "45":0,
    "50":0,
    "55":0,
    "60":0,
    "65":0,
    "70":0,
    "75":0,
    "80":0,
    "85":0,
    "90":"0",
    "95":"0",
    "100":0
  },
  {
    "DAY":"2010-01-04",
    "HOUR":13,
    "2":2549,
    "3":252,
    "5":422,
    "7":196,
    "10":70,
    "13":0,
    "16":0,
    "19":0,
    "21":0,
    "25":0,
    "30":0,
    "35":0,
    "40":0,
    "45":0,
    "50":0,
    "55":0,
    "60":0,
    "65":0,
    "70":0,
    "75":0,
    "80":0,
    "85":0,
    "90":"0",
    "95":"0",
    "100":0
  },
  {
    "DAY":"2010-01-04",
    "HOUR":14,
    "2":1729,
    "3":180,
    "5":264,
    "7":166,
    "10":140,
    "13":18,
    "16":4,
    "19":6,
    "21":2,
    "25":6,
    "30":12,
    "35":6,
    "40":8,
    "45":12,
    "50":0,
    "55":0,
    "60":0,
    "65":0,
    "70":0,
    "75":0,
    "80":0,
    "85":0,
    "90":"0",
    "95":"0",
    "100":0
  },
  {
    "DAY":"2010-01-04",
    "HOUR":15,
    "2":2163,
    "3":150,
    "5":298,
    "7":156,
    "10":72,
    "13":20,
    "16":6,
    "19":0,
    "21":3,
    "25":9,
    "30":8,
    "35":4,
    "40":14,
    "45":0,
    "50":0,
    "55":0,
    "60":0,
    "65":0,
    "70":0,
    "75":0,
    "80":0,
    "85":0,
    "90":"0",
    "95":"0",
    "100":74
  },
  {
    "DAY":"2010-01-04",
    "HOUR":16,
    "2":3407,
    "3":144,
    "5":318,
    "7":207,
    "10":344,
    "13":58,
    "16":38,
    "19":2,
    "21":8,
    "25":24,
    "30":0,
    "35":0,
    "40":0,
    "45":0,
    "50":0,
    "55":0,
    "60":0,
    "65":0,
    "70":0,
    "75":0,
    "80":0,
    "85":0,
    "90":"0",
    "95":"0",
    "100":0
  },
  {
    "DAY":"2010-01-04",
    "HOUR":17,
    "2":2490,
    "3":151,
    "5":280,
    "7":278,
    "10":190,
    "13":38,
    "16":0,
    "19":0,
    "21":0,
    "25":0,
    "30":0,
    "35":0,
    "40":0,
    "45":0,
    "50":0,
    "55":0,
    "60":0,
    "65":0,
    "70":0,
    "75":0,
    "80":0,
    "85":0,
    "90":"0",
    "95":"0",
    "100":0
  },
  {
    "DAY":"2010-01-04",
    "HOUR":18,
    "2":1916,
    "3":192,
    "5":420,
    "7":144,
    "10":66,
    "13":84,
    "16":72,
    "19":42,
    "21":16,
    "25":8,
    "30":0,
    "35":0,
    "40":0,
    "45":0,
    "50":0,
    "55":0,
    "60":0,
    "65":0,
    "70":0,
    "75":0,
    "80":0,
    "85":0,
    "90":"0",
    "95":"0",
    "100":74
  },
  {
    "DAY":"2010-01-04",
    "HOUR":19,
    "2":4048,
    "3":232,
    "5":340,
    "7":280,
    "10":208,
    "13":235,
    "16":103,
    "19":70,
    "21":24,
    "25":12,
    "30":10,
    "35":10,
    "40":0,
    "45":0,
    "50":0,
    "55":0,
    "60":0,
    "65":0,
    "70":0,
    "75":0,
    "80":0,
    "85":0,
    "90":"0",
    "95":"0",
    "100":0
  },
  {
    "DAY":"2010-01-04",
    "HOUR":20,
    "2":3293,
    "3":303,
    "5":550,
    "7":276,
    "10":237,
    "13":135,
    "16":100,
    "19":38,
    "21":8,
    "25":6,
    "30":0,
    "35":0,
    "40":0,
    "45":0,
    "50":0,
    "55":0,
    "60":0,
    "65":0,
    "70":0,
    "75":0,
    "80":0,
    "85":0,
    "90":"0",
    "95":"0",
    "100":0
  },
  {
    "DAY":"2010-01-04",
    "HOUR":21,
    "2":3513,
    "3":209,
    "5":512,
    "7":279,
    "10":288,
    "13":126,
    "16":20,
    "19":22,
    "21":6,
    "25":4,
    "30":6,
    "35":0,
    "40":0,
    "45":0,
    "50":0,
    "55":0,
    "60":0,
    "65":0,
    "70":0,
    "75":0,
    "80":0,
    "85":0,
    "90":"0",
    "95":"0",
    "100":0
  },
  {
    "DAY":"2010-01-04",
    "HOUR":22,
    "2":3237,
    "3":183,
    "5":449,
    "7":406,
    "10":377,
    "13":172,
    "16":36,
    "19":0,
    "21":0,
    "25":0,
    "30":0,
    "35":0,
    "40":0,
    "45":0,
    "50":0,
    "55":0,
    "60":0,
    "65":0,
    "70":0,
    "75":0,
    "80":0,
    "85":0,
    "90":"0",
    "95":"0",
    "100":0
  },
  {
    "DAY":"2010-01-04",
    "HOUR":23,
    "2":4085,
    "3":204,
    "5":435,
    "7":361,
    "10":378,
    "13":215,
    "16":97,
    "19":14,
    "21":8,
    "25":0,
    "30":0,
    "35":0,
    "40":0,
    "45":0,
    "50":0,
    "55":0,
    "60":0,
    "65":0,
    "70":0,
    "75":0,
    "80":0,
    "85":0,
    "90":"0",
    "95":"0",
    "100":0
  },
  {
    "DAY":"2010-01-05",
    "HOUR":0,
    "2":3575,
    "3":177,
    "5":395,
    "7":304,
    "10":275,
    "13":262,
    "16":92,
    "19":32,
    "21":0,
    "25":0,
    "30":0,
    "35":0,
    "40":0,
    "45":0,
    "50":0,
    "55":0,
    "60":0,
    "65":0,
    "70":0,
    "75":0,
    "80":0,
    "85":0,
    "90":"0",
    "95":"0",
    "100":0
  },
  {
    "DAY":"2010-01-05",
    "HOUR":1,
    "2":2653,
    "3":224,
    "5":352,
    "7":206,
    "10":273,
    "13":119,
    "16":8,
    "19":0,
    "21":0,
    "25":0,
    "30":0,
    "35":0,
    "40":0,
    "45":0,
    "50":0,
    "55":0,
    "60":0,
    "65":0,
    "70":0,
    "75":0,
    "80":0,
    "85":0,
    "90":"0",
    "95":"0",
    "100":0
  },
  {
    "DAY":"2010-01-05",
    "HOUR":2,
    "2":3250,
    "3":124,
    "5":310,
    "7":244,
    "10":312,
    "13":178,
    "16":20,
    "19":44,
    "21":4,
    "25":2,
    "30":4,
    "35":10,
    "40":0,
    "45":0,
    "50":0,
    "55":0,
    "60":0,
    "65":0,
    "70":0,
    "75":0,
    "80":0,
    "85":0,
    "90":"0",
    "95":"0",
    "100":0
  },
  {
    "DAY":"2010-01-05",
    "HOUR":3,
    "2":4215,
    "3":194,
    "5":386,
    "7":350,
    "10":316,
    "13":220,
    "16":88,
    "19":8,
    "21":8,
    "25":0,
    "30":0,
    "35":0,
    "40":0,
    "45":0,
    "50":0,
    "55":0,
    "60":0,
    "65":0,
    "70":0,
    "75":0,
    "80":0,
    "85":0,
    "90":"0",
    "95":"0",
    "100":0
  },
  {
    "DAY":"2010-01-05",
    "HOUR":4,
    "2":2813,
    "3":190,
    "5":408,
    "7":313,
    "10":264,
    "13":153,
    "16":26,
    "19":30,
    "21":4,
    "25":16,
    "30":26,
    "35":4,
    "40":0,
    "45":0,
    "50":0,
    "55":0,
    "60":0,
    "65":0,
    "70":0,
    "75":0,
    "80":0,
    "85":0,
    "90":"0",
    "95":"0",
    "100":0
  },
  {
    "DAY":"2010-01-05",
    "HOUR":5,
    "2":2907,
    "3":185,
    "5":399,
    "7":246,
    "10":194,
    "13":48,
    "16":6,
    "19":4,
    "21":2,
    "25":6,
    "30":16,
    "35":16,
    "40":12,
    "45":4,
    "50":4,
    "55":0,
    "60":0,
    "65":0,
    "70":4,
    "75":0,
    "80":6,
    "85":2,
    "90":"0",
    "95":"0",
    "100":0
  },
  {
    "DAY":"2010-01-05",
    "HOUR":6,
    "2":2118,
    "3":188,
    "5":265,
    "7":167,
    "10":153,
    "13":39,
    "16":20,
    "19":10,
    "21":16,
    "25":30,
    "30":0,
    "35":0,
    "40":0,
    "45":0,
    "50":0,
    "55":0,
    "60":0,
    "65":0,
    "70":0,
    "75":0,
    "80":0,
    "85":0,
    "90":"0",
    "95":"0",
    "100":0
  },
  {
    "DAY":"2010-01-05",
    "HOUR":7,
    "2":1645,
    "3":184,
    "5":200,
    "7":144,
    "10":114,
    "13":90,
    "16":22,
    "19":2,
    "21":10,
    "25":40,
    "30":16,
    "35":2,
    "40":0,
    "45":0,
    "50":0,
    "55":0,
    "60":0,
    "65":0,
    "70":0,
    "75":0,
    "80":0,
    "85":0,
    "90":"0",
    "95":"0",
    "100":0
  },
  {
    "DAY":"2010-01-05",
    "HOUR":8,
    "2":3446,
    "3":268,
    "5":654,
    "7":433,
    "10":334,
    "13":92,
    "16":18,
    "19":2,
    "21":16,
    "25":4,
    "30":0,
    "35":0,
    "40":0,
    "45":0,
    "50":0,
    "55":0,
    "60":0,
    "65":0,
    "70":0,
    "75":0,
    "80":0,
    "85":0,
    "90":"0",
    "95":"0",
    "100":76
  },
  {
    "DAY":"2010-01-05",
    "HOUR":9,
    "2":2568,
    "3":289,
    "5":540,
    "7":244,
    "10":168,
    "13":18,
    "16":12,
    "19":8,
    "21":0,
    "25":0,
    "30":0,
    "35":0,
    "40":0,
    "45":0,
    "50":0,
    "55":0,
    "60":0,
    "65":0,
    "70":0,
    "75":0,
    "80":0,
    "85":0,
    "90":"0",
    "95":"0",
    "100":0
  },
  {
    "DAY":"2010-01-05",
    "HOUR":10,
    "2":1694,
    "3":272,
    "5":364,
    "7":148,
    "10":91,
    "13":55,
    "16":10,
    "19":12,
    "21":0,
    "25":0,
    "30":0,
    "35":0,
    "40":0,
    "45":0,
    "50":0,
    "55":0,
    "60":0,
    "65":0,
    "70":0,
    "75":0,
    "80":0,
    "85":0,
    "90":"0",
    "95":"0",
    "100":0
  },
  {
    "DAY":"2010-01-05",
    "HOUR":11,
    "2":3730,
    "3":258,
    "5":469,
    "7":353,
    "10":327,
    "13":151,
    "16":49,
    "19":22,
    "21":6,
    "25":10,
    "30":0,
    "35":0,
    "40":0,
    "45":0,
    "50":0,
    "55":0,
    "60":0,
    "65":0,
    "70":0,
    "75":0,
    "80":0,
    "85":0,
    "90":"0",
    "95":"0",
    "100":74
  },
  {
    "DAY":"2010-01-05",
    "HOUR":12,
    "2":3083,
    "3":231,
    "5":342,
    "7":195,
    "10":148,
    "13":104,
    "16":80,
    "19":34,
    "21":40,
    "25":54,
    "30":6,
    "35":14,
    "40":0,
    "45":0,
    "50":0,
    "55":0,
    "60":0,
    "65":0,
    "70":0,
    "75":0,
    "80":0,
    "85":0,
    "90":"0",
    "95":"0",
    "100":0
  },
  {
    "DAY":"2010-01-05",
    "HOUR":13,
    "2":2329,
    "3":132,
    "5":236,
    "7":128,
    "10":172,
    "13":112,
    "16":48,
    "19":40,
    "21":24,
    "25":4,
    "30":0,
    "35":0,
    "40":0,
    "45":0,
    "50":0,
    "55":0,
    "60":0,
    "65":0,
    "70":0,
    "75":0,
    "80":0,
    "85":0,
    "90":"0",
    "95":"0",
    "100":0
  },
  {
    "DAY":"2010-01-05",
    "HOUR":14,
    "2":2294,
    "3":138,
    "5":207,
    "7":132,
    "10":159,
    "13":150,
    "16":136,
    "19":94,
    "21":14,
    "25":34,
    "30":58,
    "35":10,
    "40":12,
    "45":8,
    "50":6,
    "55":4,
    "60":6,
    "65":0,
    "70":0,
    "75":2,
    "80":2,
    "85":2,
    "90":"0",
    "95":"0",
    "100":122
  },
  {
    "DAY":"2010-01-05",
    "HOUR":15,
    "2":3350,
    "3":412,
    "5":512,
    "7":298,
    "10":208,
    "13":104,
    "16":38,
    "19":24,
    "21":11,
    "25":6,
    "30":23,
    "35":4,
    "40":8,
    "45":2,
    "50":0,
    "55":0,
    "60":4,
    "65":24,
    "70":0,
    "75":0,
    "80":0,
    "85":0,
    "90":"0",
    "95":"0",
    "100":76
  },
  {
    "DAY":"2010-01-05",
    "HOUR":16,
    "2":1442,
    "3":80,
    "5":146,
    "7":152,
    "10":156,
    "13":60,
    "16":42,
    "19":10,
    "21":8,
    "25":4,
    "30":0,
    "35":0,
    "40":0,
    "45":0,
    "50":0,
    "55":0,
    "60":0,
    "65":0,
    "70":0,
    "75":0,
    "80":0,
    "85":0,
    "90":"0",
    "95":"0",
    "100":0
  },
  {
    "DAY":"2010-01-05",
    "HOUR":17,
    "2":3413,
    "3":220,
    "5":316,
    "7":206,
    "10":236,
    "13":125,
    "16":152,
    "19":79,
    "21":24,
    "25":44,
    "30":4,
    "35":0,
    "40":0,
    "45":0,
    "50":0,
    "55":0,
    "60":0,
    "65":0,
    "70":0,
    "75":0,
    "80":0,
    "85":0,
    "90":"0",
    "95":"0",
    "100":0
  },
  {
    "DAY":"2010-01-05",
    "HOUR":18,
    "2":2600,
    "3":234,
    "5":440,
    "7":274,
    "10":162,
    "13":54,
    "16":42,
    "19":38,
    "21":4,
    "25":0,
    "30":0,
    "35":0,
    "40":0,
    "45":0,
    "50":0,
    "55":0,
    "60":0,
    "65":0,
    "70":0,
    "75":0,
    "80":0,
    "85":0,
    "90":"0",
    "95":"0",
    "100":68
  },
  {
    "DAY":"2010-01-05",
    "HOUR":19,
    "2":2139,
    "3":82,
    "5":275,
    "7":182,
    "10":212,
    "13":100,
    "16":54,
    "19":12,
    "21":2,
    "25":8,
    "30":0,
    "35":0,
    "40":0,
    "45":0,
    "50":0,
    "55":0,
    "60":0,
    "65":0,
    "70":0,
    "75":0,
    "80":0,
    "85":0,
    "90":"0",
    "95":"0",
    "100":0
  },
  {
    "DAY":"2010-01-05",
    "HOUR":20,
    "2":3743,
    "3":159,
    "5":328,
    "7":318,
    "10":303,
    "13":196,
    "16":78,
    "19":22,
    "21":10,
    "25":0,
    "30":0,
    "35":0,
    "40":0,
    "45":0,
    "50":0,
    "55":0,
    "60":0,
    "65":0,
    "70":0,
    "75":0,
    "80":0,
    "85":0,
    "90":"0",
    "95":"0",
    "100":0
  },
  {
    "DAY":"2010-01-05",
    "HOUR":21,
    "2":1797,
    "3":135,
    "5":222,
    "7":102,
    "10":107,
    "13":59,
    "16":26,
    "19":28,
    "21":32,
    "25":38,
    "30":12,
    "35":0,
    "40":0,
    "45":0,
    "50":0,
    "55":0,
    "60":0,
    "65":0,
    "70":0,
    "75":0,
    "80":0,
    "85":0,
    "90":"0",
    "95":"0",
    "100":0
  },
  {
    "DAY":"2010-01-05",
    "HOUR":22,
    "2":3401,
    "3":115,
    "5":308,
    "7":334,
    "10":328,
    "13":258,
    "16":106,
    "19":138,
    "21":46,
    "25":36,
    "30":10,
    "35":0,
    "40":0,
    "45":0,
    "50":0,
    "55":0,
    "60":0,
    "65":0,
    "70":0,
    "75":0,
    "80":0,
    "85":0,
    "90":"0",
    "95":"0",
    "100":0
  },
  {
    "DAY":"2010-01-05",
    "HOUR":23,
    "2":2952,
    "3":244,
    "5":407,
    "7":219,
    "10":118,
    "13":102,
    "16":34,
    "19":42,
    "21":18,
    "25":0,
    "30":0,
    "35":0,
    "40":0,
    "45":0,
    "50":0,
    "55":0,
    "60":0,
    "65":0,
    "70":0,
    "75":0,
    "80":0,
    "85":0,
    "90":"0",
    "95":"0",
    "100":0
  },
  {
    "DAY":"2010-01-06",
    "HOUR":0,
    "2":2751,
    "3":168,
    "5":376,
    "7":231,
    "10":277,
    "13":128,
    "16":72,
    "19":6,
    "21":8,
    "25":0,
    "30":0,
    "35":0,
    "40":0,
    "45":0,
    "50":0,
    "55":0,
    "60":0,
    "65":0,
    "70":0,
    "75":0,
    "80":0,
    "85":0,
    "90":"0",
    "95":"0",
    "100":0
  },
  {
    "DAY":"2010-01-06",
    "HOUR":1,
    "2":1840,
    "3":128,
    "5":221,
    "7":139,
    "10":213,
    "13":102,
    "16":30,
    "19":16,
    "21":2,
    "25":14,
    "30":14,
    "35":0,
    "40":0,
    "45":0,
    "50":0,
    "55":0,
    "60":0,
    "65":0,
    "70":0,
    "75":0,
    "80":0,
    "85":0,
    "90":"0",
    "95":"0",
    "100":0
  },
  {
    "DAY":"2010-01-06",
    "HOUR":2,
    "2":2760,
    "3":116,
    "5":267,
    "7":219,
    "10":183,
    "13":154,
    "16":85,
    "19":22,
    "21":12,
    "25":2,
    "30":12,
    "35":10,
    "40":0,
    "45":0,
    "50":0,
    "55":0,
    "60":0,
    "65":0,
    "70":0,
    "75":0,
    "80":0,
    "85":0,
    "90":"0",
    "95":"0",
    "100":74
  },
  {
    "DAY":"2010-01-06",
    "HOUR":3,
    "2":3016,
    "3":199,
    "5":385,
    "7":411,
    "10":328,
    "13":105,
    "16":87,
    "19":53,
    "21":0,
    "25":0,
    "30":0,
    "35":0,
    "40":0,
    "45":0,
    "50":0,
    "55":0,
    "60":0,
    "65":0,
    "70":0,
    "75":0,
    "80":0,
    "85":0,
    "90":"0",
    "95":"0",
    "100":0
  },
  {
    "DAY":"2010-01-06",
    "HOUR":4,
    "2":3568,
    "3":216,
    "5":397,
    "7":249,
    "10":283,
    "13":209,
    "16":114,
    "19":68,
    "21":12,
    "25":10,
    "30":0,
    "35":0,
    "40":0,
    "45":0,
    "50":0,
    "55":0,
    "60":0,
    "65":0,
    "70":0,
    "75":0,
    "80":0,
    "85":0,
    "90":"0",
    "95":"0",
    "100":0
  },
  {
    "DAY":"2010-01-06",
    "HOUR":5,
    "2":2739,
    "3":262,
    "5":318,
    "7":226,
    "10":250,
    "13":80,
    "16":42,
    "19":10,
    "21":6,
    "25":0,
    "30":0,
    "35":0,
    "40":0,
    "45":0,
    "50":0,
    "55":0,
    "60":0,
    "65":0,
    "70":0,
    "75":0,
    "80":0,
    "85":0,
    "90":"0",
    "95":"0",
    "100":0
  },
  {
    "DAY":"2010-01-06",
    "HOUR":6,
    "2":3730,
    "3":219,
    "5":356,
    "7":240,
    "10":255,
    "13":213,
    "16":99,
    "19":40,
    "21":22,
    "25":20,
    "30":0,
    "35":0,
    "40":0,
    "45":0,
    "50":0,
    "55":0,
    "60":0,
    "65":0,
    "70":0,
    "75":0,
    "80":0,
    "85":0,
    "90":"0",
    "95":"0",
    "100":0
  },
  {
    "DAY":"2010-01-06",
    "HOUR":7,
    "2":2632,
    "3":127,
    "5":265,
    "7":181,
    "10":240,
    "13":118,
    "16":58,
    "19":18,
    "21":8,
    "25":8,
    "30":12,
    "35":2,
    "40":0,
    "45":0,
    "50":0,
    "55":0,
    "60":0,
    "65":0,
    "70":0,
    "75":0,
    "80":0,
    "85":0,
    "90":"0",
    "95":"0",
    "100":0
  },
  {
    "DAY":"2010-01-06",
    "HOUR":8,
    "2":3630,
    "3":245,
    "5":475,
    "7":356,
    "10":312,
    "13":166,
    "16":80,
    "19":0,
    "21":0,
    "25":0,
    "30":0,
    "35":0,
    "40":0,
    "45":0,
    "50":0,
    "55":0,
    "60":0,
    "65":0,
    "70":0,
    "75":0,
    "80":0,
    "85":0,
    "90":"0",
    "95":"0",
    "100":0
  },
  {
    "DAY":"2010-01-06",
    "HOUR":9,
    "2":2361,
    "3":199,
    "5":395,
    "7":217,
    "10":165,
    "13":120,
    "16":23,
    "19":5,
    "21":0,
    "25":0,
    "30":0,
    "35":0,
    "40":0,
    "45":0,
    "50":0,
    "55":0,
    "60":0,
    "65":0,
    "70":0,
    "75":0,
    "80":0,
    "85":0,
    "90":"0",
    "95":"0",
    "100":75
  },
  {
    "DAY":"2010-01-06",
    "HOUR":10,
    "2":3113,
    "3":132,
    "5":286,
    "7":250,
    "10":337,
    "13":228,
    "16":118,
    "19":24,
    "21":18,
    "25":22,
    "30":22,
    "35":14,
    "40":14,
    "45":0,
    "50":0,
    "55":0,
    "60":0,
    "65":0,
    "70":0,
    "75":0,
    "80":0,
    "85":0,
    "90":"0",
    "95":"0",
    "100":0
  },
  {
    "DAY":"2010-01-06",
    "HOUR":11,
    "2":3909,
    "3":199,
    "5":366,
    "7":316,
    "10":254,
    "13":224,
    "16":112,
    "19":76,
    "21":12,
    "25":28,
    "30":4,
    "35":0,
    "40":0,
    "45":0,
    "50":0,
    "55":0,
    "60":0,
    "65":0,
    "70":0,
    "75":0,
    "80":0,
    "85":0,
    "90":"0",
    "95":"0",
    "100":0
  },
  {
    "DAY":"2010-01-06",
    "HOUR":12,
    "2":3526,
    "3":238,
    "5":505,
    "7":251,
    "10":347,
    "13":199,
    "16":118,
    "19":74,
    "21":34,
    "25":36,
    "30":20,
    "35":0,
    "40":0,
    "45":0,
    "50":0,
    "55":0,
    "60":0,
    "65":0,
    "70":0,
    "75":0,
    "80":0,
    "85":0,
    "90":"0",
    "95":"0",
    "100":0
  },
  {
    "DAY":"2010-01-06",
    "HOUR":13,
    "2":1934,
    "3":173,
    "5":239,
    "7":141,
    "10":96,
    "13":30,
    "16":14,
    "19":0,
    "21":0,
    "25":0,
    "30":0,
    "35":0,
    "40":0,
    "45":0,
    "50":0,
    "55":0,
    "60":0,
    "65":0,
    "70":0,
    "75":0,
    "80":0,
    "85":0,
    "90":"0",
    "95":"0",
    "100":0
  },
  {
    "DAY":"2010-01-06",
    "HOUR":14,
    "2":2184,
    "3":124,
    "5":269,
    "7":254,
    "10":166,
    "13":74,
    "16":8,
    "19":0,
    "21":0,
    "25":0,
    "30":0,
    "35":0,
    "40":0,
    "45":0,
    "50":0,
    "55":0,
    "60":0,
    "65":0,
    "70":0,
    "75":0,
    "80":0,
    "85":0,
    "90":"0",
    "95":"0",
    "100":0
  },
  {
    "DAY":"2010-01-06",
    "HOUR":15,
    "2":3017,
    "3":162,
    "5":289,
    "7":263,
    "10":300,
    "13":255,
    "16":140,
    "19":18,
    "21":2,
    "25":6,
    "30":0,
    "35":0,
    "40":0,
    "45":0,
    "50":0,
    "55":0,
    "60":0,
    "65":0,
    "70":0,
    "75":0,
    "80":0,
    "85":0,
    "90":"0",
    "95":"0",
    "100":0
  },
  {
    "DAY":"2010-01-06",
    "HOUR":16,
    "2":3575,
    "3":317,
    "5":587,
    "7":375,
    "10":388,
    "13":189,
    "16":152,
    "19":24,
    "21":2,
    "25":0,
    "30":0,
    "35":0,
    "40":0,
    "45":0,
    "50":0,
    "55":0,
    "60":0,
    "65":0,
    "70":0,
    "75":0,
    "80":0,
    "85":0,
    "90":"0",
    "95":"0",
    "100":0
  },
  {
    "DAY":"2010-01-06",
    "HOUR":17,
    "2":2647,
    "3":123,
    "5":300,
    "7":213,
    "10":152,
    "13":78,
    "16":46,
    "19":8,
    "21":0,
    "25":0,
    "30":0,
    "35":0,
    "40":0,
    "45":0,
    "50":0,
    "55":0,
    "60":0,
    "65":0,
    "70":0,
    "75":0,
    "80":0,
    "85":0,
    "90":"0",
    "95":"0",
    "100":76
  },
  {
    "DAY":"2010-01-06",
    "HOUR":18,
    "2":2424,
    "3":168,
    "5":394,
    "7":352,
    "10":230,
    "13":146,
    "16":56,
    "19":41,
    "21":19,
    "25":4,
    "30":0,
    "35":0,
    "40":0,
    "45":0,
    "50":0,
    "55":0,
    "60":0,
    "65":0,
    "70":0,
    "75":0,
    "80":0,
    "85":0,
    "90":"0",
    "95":"0",
    "100":0
  },
  {
    "DAY":"2010-01-06",
    "HOUR":19,
    "2":1960,
    "3":178,
    "5":248,
    "7":86,
    "10":26,
    "13":0,
    "16":0,
    "19":0,
    "21":0,
    "25":0,
    "30":0,
    "35":0,
    "40":0,
    "45":0,
    "50":0,
    "55":0,
    "60":0,
    "65":0,
    "70":0,
    "75":0,
    "80":0,
    "85":0,
    "90":"0",
    "95":"0",
    "100":0
  },
  {
    "DAY":"2010-01-06",
    "HOUR":20,
    "2":3704,
    "3":347,
    "5":643,
    "7":234,
    "10":269,
    "13":103,
    "16":60,
    "19":14,
    "21":14,
    "25":8,
    "30":0,
    "35":0,
    "40":0,
    "45":0,
    "50":0,
    "55":0,
    "60":0,
    "65":0,
    "70":0,
    "75":0,
    "80":0,
    "85":0,
    "90":"0",
    "95":"0",
    "100":70
  },
  {
    "DAY":"2010-01-06",
    "HOUR":21,
    "2":3543,
    "3":182,
    "5":363,
    "7":386,
    "10":355,
    "13":230,
    "16":54,
    "19":30,
    "21":10,
    "25":16,
    "30":4,
    "35":0,
    "40":0,
    "45":0,
    "50":0,
    "55":0,
    "60":0,
    "65":0,
    "70":0,
    "75":0,
    "80":0,
    "85":0,
    "90":"0",
    "95":"0",
    "100":0
  },
  {
    "DAY":"2010-01-06",
    "HOUR":22,
    "2":3763,
    "3":157,
    "5":281,
    "7":255,
    "10":347,
    "13":304,
    "16":162,
    "19":32,
    "21":16,
    "25":8,
    "30":0,
    "35":0,
    "40":0,
    "45":0,
    "50":0,
    "55":0,
    "60":0,
    "65":0,
    "70":0,
    "75":0,
    "80":0,
    "85":0,
    "90":"0",
    "95":"0",
    "100":0
  },
  {
    "DAY":"2010-01-06",
    "HOUR":23,
    "2":3705,
    "3":187,
    "5":292,
    "7":291,
    "10":349,
    "13":170,
    "16":74,
    "19":22,
    "21":4,
    "25":2,
    "30":4,
    "35":10,
    "40":0,
    "45":0,
    "50":0,
    "55":0,
    "60":0,
    "65":0,
    "70":0,
    "75":0,
    "80":0,
    "85":0,
    "90":"0",
    "95":"0",
    "100":0
  },
  {
    "DAY":"2010-01-07",
    "HOUR":0,
    "2":2990,
    "3":87,
    "5":193,
    "7":187,
    "10":272,
    "13":209,
    "16":53,
    "19":35,
    "21":2,
    "25":22,
    "30":2,
    "35":0,
    "40":0,
    "45":0,
    "50":0,
    "55":0,
    "60":0,
    "65":0,
    "70":0,
    "75":0,
    "80":0,
    "85":0,
    "90":"0",
    "95":"0",
    "100":74
  },
  {
    "DAY":"2010-01-07",
    "HOUR":1,
    "2":3667,
    "3":148,
    "5":333,
    "7":284,
    "10":274,
    "13":266,
    "16":128,
    "19":30,
    "21":26,
    "25":14,
    "30":0,
    "35":0,
    "40":0,
    "45":0,
    "50":0,
    "55":0,
    "60":0,
    "65":0,
    "70":0,
    "75":0,
    "80":0,
    "85":0,
    "90":"0",
    "95":"0",
    "100":0
  },
  {
    "DAY":"2010-01-07",
    "HOUR":2,
    "2":1390,
    "3":79,
    "5":114,
    "7":105,
    "10":196,
    "13":106,
    "16":8,
    "19":0,
    "21":0,
    "25":0,
    "30":0,
    "35":0,
    "40":0,
    "45":0,
    "50":0,
    "55":0,
    "60":0,
    "65":0,
    "70":0,
    "75":0,
    "80":0,
    "85":0,
    "90":"0",
    "95":"0",
    "100":0
  },
  {
    "DAY":"2010-01-07",
    "HOUR":3,
    "2":1581,
    "3":43,
    "5":141,
    "7":127,
    "10":186,
    "13":141,
    "16":35,
    "19":3,
    "21":0,
    "25":0,
    "30":0,
    "35":0,
    "40":0,
    "45":0,
    "50":0,
    "55":0,
    "60":0,
    "65":0,
    "70":0,
    "75":0,
    "80":0,
    "85":0,
    "90":"0",
    "95":"0",
    "100":0
  },
  {
    "DAY":"2010-01-07",
    "HOUR":4,
    "2":1863,
    "3":72,
    "5":140,
    "7":114,
    "10":174,
    "13":156,
    "16":72,
    "19":22,
    "21":14,
    "25":14,
    "30":2,
    "35":4,
    "40":0,
    "45":0,
    "50":0,
    "55":0,
    "60":0,
    "65":0,
    "70":0,
    "75":0,
    "80":0,
    "85":0,
    "90":"0",
    "95":"0",
    "100":72
  },
  {
    "DAY":"2010-01-07",
    "HOUR":5,
    "2":1962,
    "3":67,
    "5":206,
    "7":152,
    "10":205,
    "13":146,
    "16":76,
    "19":28,
    "21":5,
    "25":11,
    "30":1,
    "35":0,
    "40":0,
    "45":0,
    "50":0,
    "55":0,
    "60":0,
    "65":0,
    "70":0,
    "75":0,
    "80":0,
    "85":0,
    "90":"0",
    "95":"0",
    "100":0
  },
  {
    "DAY":"2010-01-07",
    "HOUR":6,
    "2":960,
    "3":42,
    "5":102,
    "7":69,
    "10":72,
    "13":86,
    "16":64,
    "19":17,
    "21":10,
    "25":15,
    "30":4,
    "35":0,
    "40":1,
    "45":0,
    "50":0,
    "55":0,
    "60":0,
    "65":0,
    "70":0,
    "75":0,
    "80":0,
    "85":0,
    "90":"0",
    "95":"0",
    "100":0
  }
]