[
  {
    "DAY":"2010-07-28",
    "HOUR":21,
    "2":2697,
    "3":75,
    "5":230,
    "7":214,
    "10":216,
    "13":124,
    "16":92,
    "19":50,
    "21":32,
    "25":44,
    "30":8,
    "35":0,
    "40":0,
    "45":0,
    "50":0,
    "55":0,
    "60":0,
    "65":0,
    "70":0,
    "75":"0",
    "80":0,
    "85":0,
    "90":0,
    "95":0,
    "100":0
  },
  {
    "DAY":"2010-07-28",
    "HOUR":22,
    "2":3423,
    "3":162,
    "5":304,
    "7":184,
    "10":188,
    "13":136,
    "16":82,
    "19":104,
    "21":22,
    "25":36,
    "30":20,
    "35":0,
    "40":0,
    "45":0,
    "50":0,
    "55":0,
    "60":0,
    "65":0,
    "70":0,
    "75":"0",
    "80":0,
    "85":0,
    "90":0,
    "95":0,
    "100":0
  },
  {
    "DAY":"2010-07-28",
    "HOUR":23,
    "2":3627,
    "3":227,
    "5":311,
    "7":194,
    "10":186,
    "13":106,
    "16":68,
    "19":56,
    "21":20,
    "25":16,
    "30":0,
    "35":0,
    "40":0,
    "45":0,
    "50":0,
    "55":0,
    "60":0,
    "65":0,
    "70":0,
    "75":"0",
    "80":0,
    "85":0,
    "90":0,
    "95":0,
    "100":0
  },
  {
    "DAY":"2010-07-29",
    "HOUR":0,
    "2":3551,
    "3":223,
    "5":277,
    "7":289,
    "10":141,
    "13":118,
    "16":94,
    "19":30,
    "21":14,
    "25":46,
    "30":16,
    "35":8,
    "40":18,
    "45":8,
    "50":2,
    "55":0,
    "60":0,
    "65":0,
    "70":0,
    "75":"0",
    "80":0,
    "85":0,
    "90":0,
    "95":0,
    "100":0
  },
  {
    "DAY":"2010-07-29",
    "HOUR":1,
    "2":3016,
    "3":218,
    "5":342,
    "7":210,
    "10":174,
    "13":120,
    "16":58,
    "19":32,
    "21":14,
    "25":18,
    "30":0,
    "35":0,
    "40":0,
    "45":0,
    "50":0,
    "55":0,
    "60":0,
    "65":0,
    "70":0,
    "75":"0",
    "80":0,
    "85":0,
    "90":0,
    "95":0,
    "100":54
  },
  {
    "DAY":"2010-07-29",
    "HOUR":2,
    "2":3860,
    "3":162,
    "5":294,
    "7":268,
    "10":280,
    "13":104,
    "16":52,
    "19":38,
    "21":14,
    "25":0,
    "30":0,
    "35":0,
    "40":0,
    "45":0,
    "50":0,
    "55":0,
    "60":0,
    "65":0,
    "70":0,
    "75":"0",
    "80":0,
    "85":0,
    "90":0,
    "95":0,
    "100":0
  },
  {
    "DAY":"2010-07-29",
    "HOUR":3,
    "2":2558,
    "3":102,
    "5":186,
    "7":158,
    "10":104,
    "13":98,
    "16":2,
    "19":0,
    "21":0,
    "25":0,
    "30":0,
    "35":0,
    "40":0,
    "45":0,
    "50":0,
    "55":0,
    "60":0,
    "65":0,
    "70":0,
    "75":"0",
    "80":0,
    "85":0,
    "90":0,
    "95":0,
    "100":0
  },
  {
    "DAY":"2010-07-29",
    "HOUR":4,
    "2":3945,
    "3":163,
    "5":233,
    "7":191,
    "10":140,
    "13":216,
    "16":118,
    "19":52,
    "21":14,
    "25":6,
    "30":0,
    "35":0,
    "40":0,
    "45":0,
    "50":0,
    "55":0,
    "60":0,
    "65":0,
    "70":0,
    "75":"0",
    "80":0,
    "85":0,
    "90":0,
    "95":0,
    "100":0
  },
  {
    "DAY":"2010-07-29",
    "HOUR":5,
    "2":3242,
    "3":150,
    "5":266,
    "7":216,
    "10":258,
    "13":198,
    "16":50,
    "19":22,
    "21":0,
    "25":0,
    "30":4,
    "35":0,
    "40":0,
    "45":0,
    "50":0,
    "55":0,
    "60":0,
    "65":0,
    "70":0,
    "75":"0",
    "80":0,
    "85":0,
    "90":0,
    "95":0,
    "100":306
  },
  {
    "DAY":"2010-07-29",
    "HOUR":6,
    "2":2003,
    "3":258,
    "5":348,
    "7":140,
    "10":112,
    "13":64,
    "16":18,
    "19":16,
    "21":2,
    "25":16,
    "30":0,
    "35":0,
    "40":0,
    "45":0,
    "50":0,
    "55":0,
    "60":0,
    "65":0,
    "70":0,
    "75":"0",
    "80":0,
    "85":0,
    "90":0,
    "95":0,
    "100":40
  },
  {
    "DAY":"2010-07-29",
    "HOUR":7,
    "2":2816,
    "3":120,
    "5":296,
    "7":188,
    "10":236,
    "13":118,
    "16":38,
    "19":22,
    "21":16,
    "25":2,
    "30":0,
    "35":0,
    "40":0,
    "45":0,
    "50":0,
    "55":0,
    "60":0,
    "65":0,
    "70":0,
    "75":"0",
    "80":0,
    "85":0,
    "90":0,
    "95":0,
    "100":258
  },
  {
    "DAY":"2010-07-29",
    "HOUR":8,
    "2":3456,
    "3":175,
    "5":311,
    "7":199,
    "10":162,
    "13":125,
    "16":94,
    "19":24,
    "21":26,
    "25":16,
    "30":36,
    "35":0,
    "40":0,
    "45":0,
    "50":0,
    "55":0,
    "60":0,
    "65":0,
    "70":0,
    "75":"0",
    "80":0,
    "85":0,
    "90":0,
    "95":0,
    "100":306
  },
  {
    "DAY":"2010-07-29",
    "HOUR":9,
    "2":3226,
    "3":171,
    "5":328,
    "7":214,
    "10":216,
    "13":204,
    "16":60,
    "19":26,
    "21":14,
    "25":16,
    "30":10,
    "35":4,
    "40":10,
    "45":0,
    "50":0,
    "55":0,
    "60":0,
    "65":0,
    "70":0,
    "75":"0",
    "80":0,
    "85":0,
    "90":0,
    "95":0,
    "100":0
  },
  {
    "DAY":"2010-07-29",
    "HOUR":10,
    "2":4122,
    "3":142,
    "5":225,
    "7":205,
    "10":157,
    "13":79,
    "16":58,
    "19":52,
    "21":38,
    "25":37,
    "30":24,
    "35":0,
    "40":0,
    "45":0,
    "50":0,
    "55":0,
    "60":0,
    "65":0,
    "70":0,
    "75":"0",
    "80":0,
    "85":0,
    "90":0,
    "95":0,
    "100":0
  },
  {
    "DAY":"2010-07-29",
    "HOUR":11,
    "2":3304,
    "3":141,
    "5":273,
    "7":230,
    "10":179,
    "13":199,
    "16":132,
    "19":41,
    "21":45,
    "25":32,
    "30":34,
    "35":22,
    "40":0,
    "45":0,
    "50":0,
    "55":0,
    "60":0,
    "65":0,
    "70":0,
    "75":"0",
    "80":0,
    "85":0,
    "90":0,
    "95":0,
    "100":0
  },
  {
    "DAY":"2010-07-29",
    "HOUR":12,
    "2":4243,
    "3":205,
    "5":327,
    "7":296,
    "10":268,
    "13":158,
    "16":119,
    "19":94,
    "21":38,
    "25":72,
    "30":38,
    "35":42,
    "40":8,
    "45":0,
    "50":0,
    "55":0,
    "60":0,
    "65":0,
    "70":0,
    "75":"0",
    "80":0,
    "85":0,
    "90":0,
    "95":0,
    "100":0
  },
  {
    "DAY":"2010-07-29",
    "HOUR":13,
    "2":2025,
    "3":62,
    "5":110,
    "7":95,
    "10":144,
    "13":83,
    "16":62,
    "19":42,
    "21":18,
    "25":27,
    "30":21,
    "35":3,
    "40":0,
    "45":0,
    "50":0,
    "55":0,
    "60":0,
    "65":0,
    "70":0,
    "75":"0",
    "80":0,
    "85":0,
    "90":0,
    "95":0,
    "100":0
  },
  {
    "DAY":"2010-07-29",
    "HOUR":14,
    "2":1702,
    "3":82,
    "5":124,
    "7":66,
    "10":79,
    "13":46,
    "16":43,
    "19":15,
    "21":4,
    "25":0,
    "30":0,
    "35":0,
    "40":0,
    "45":0,
    "50":0,
    "55":0,
    "60":0,
    "65":0,
    "70":0,
    "75":"0",
    "80":0,
    "85":0,
    "90":0,
    "95":0,
    "100":0
  },
  {
    "DAY":"2010-07-29",
    "HOUR":15,
    "2":1832,
    "3":152,
    "5":219,
    "7":156,
    "10":149,
    "13":38,
    "16":27,
    "19":27,
    "21":2,
    "25":1,
    "30":5,
    "35":1,
    "40":0,
    "45":0,
    "50":0,
    "55":0,
    "60":0,
    "65":0,
    "70":0,
    "75":"0",
    "80":0,
    "85":0,
    "90":0,
    "95":0,
    "100":80
  },
  {
    "DAY":"2010-07-29",
    "HOUR":16,
    "2":1608,
    "3":127,
    "5":198,
    "7":120,
    "10":113,
    "13":43,
    "16":8,
    "19":11,
    "21":3,
    "25":1,
    "30":0,
    "35":0,
    "40":0,
    "45":0,
    "50":0,
    "55":0,
    "60":0,
    "65":0,
    "70":0,
    "75":"0",
    "80":0,
    "85":0,
    "90":0,
    "95":0,
    "100":40
  }
]
